AbPyTools-0.2.5.dist-info/METADATA
AbPyTools-0.2.5.dist-info/RECORD
AbPyTools-0.2.5.dist-info/WHEEL
AbPyTools-0.2.5.dist-info/top_level.txt
abpytools/__about__.py
abpytools/__init__.py
abpytools/home.py
abpytools/analysis/__init__.py
abpytools/analysis/amino_acid_freq.py
abpytools/analysis/analysis_helper_functions.py
abpytools/analysis/cdr_length.py
abpytools/analysis/cluster.py
abpytools/analysis/distance.py
abpytools/analysis/distance_metrics.py
abpytools/analysis/sequence_alignment.py
abpytools/core/__init__.py
abpytools/core/base.py
abpytools/core/cache.py
abpytools/core/chain.py
abpytools/core/chain_collection.py
abpytools/core/fab.py
abpytools/core/fab_collection.py
abpytools/core/helper_functions.py
abpytools/data/AminoAcidProperties.json
abpytools/data/CDR_positions.json
abpytools/data/Framework_positions.json
abpytools/data/NumberingSchemes.json
abpytools/features/__init__.py
abpytools/features/cdr.py
abpytools/features/composition.py
abpytools/features/regions.py
abpytools/utils/__init__.py
abpytools/utils/abpytools_exceptions.py
abpytools/utils/data_loader.py
abpytools/utils/downloads.py
abpytools/utils/math_utils.py
abpytools/utils/python_config.py
