Metadata-Version: 2.1
Name: AbPyTools
Version: 0.2.5
Summary: Python package for antibody analysis
Home-page: https://github.com/gf712/AbPyTools
Author: Gil Ferreira Hoben
Author-email: gil.hoben.16@ucl.ac.uk
License: MIT
Keywords: antibody-analysis bioinformatics data-processing
Platform: UNKNOWN
Classifier: Development Status :: 2 - Pre-Alpha
Classifier: Intended Audience :: Science/Research
Classifier: License :: OSI Approved :: MIT License
Classifier: Natural Language :: English
Classifier: Programming Language :: Python :: 3 :: Only
Classifier: Topic :: Scientific/Engineering :: Bio-Informatics
Requires-Dist: numpy
Requires-Dist: joblib
Requires-Dist: pandas
Requires-Dist: tqdm (>=4.15)
Requires-Dist: seaborn
Requires-Dist: matplotlib
Requires-Dist: beautifulsoup4
Requires-Dist: lxml
Requires-Dist: scipy
